{
  "report_id": "NGR-60322",
  "name": "Pflanzen-appio",
  "total_score": 96,
  "ampel": "GRUEN",
  "checks": {
    "domain": {
      "com": true,
      "de": true,
      "app": true,
      "io": true,
      "score": 100,
      "details": {
        "checked": [
          "pflanzenappio.com",
          "pflanzenappio.de",
          "pflanzenappio.app",
          "pflanzenappio.io"
        ],
        "source": "STUB"
      }
    },
    "store": {
      "apple": true,
      "google": true,
      "score": 100,
      "details": {
        "apple_search": "'Pflanzen-appio' on App Store",
        "google_search": "'Pflanzen-appio' on Play Store",
        "source": "STUB"
      }
    },
    "social_media": {
      "instagram": true,
      "tiktok": true,
      "x": true,
      "youtube": true,
      "linkedin": true,
      "score": 100,
      "details": {
        "handle_checked": "@pflanzenappio",
        "source": "STUB"
      }
    },
    "trademark": {
      "dpma": true,
      "euipo": true,
      "score": 100,
      "hard_blocker": false
    },
    "brand_fit": {
      "tonality": 62,
      "pronounceability": 48,
      "memorability": 92,
      "confusion_risk": 98,
      "international": 87,
      "score": 77,
      "recommendation": "Acceptable. Minor concerns noted."
    },
    "aso": {
      "keyword_saturation": "medium",
      "dominant_competitors": [
        "AppX",
        "QuickApp"
      ],
      "score": 60
    }
  },
  "hard_blockers": [],
  "soft_blockers": [],
  "recommendations": [
    "Name looks strong across all dimensions. Proceed with confidence."
  ],
  "alternatives": [],
  "ceo_decision": null,
  "iteration": 1,
  "timestamp": "2026-03-31T19:20:10.312128+00:00"
}