{
  "run_id": "20260323_000714",
  "generated": "2026-03-23T00:13:34",
  "proposal_count": 1,
  "proposals": [
    {
      "title": "SwiftUI lifecycle pattern: Memory Leak in `StorageManager`",
      "type": "technical_pattern",
      "lesson": "Generated SwiftUI code missing lifecycle management: Memory Leak in `StorageManager`",
      "evidence": "Bug Hunter finding in run 20260323_000714",
      "source_run": "20260323_000714",
      "source_project": "askfin",
      "confidence": "hypothesis",
      "tags": [
        "swiftui",
        "lifecycle",
        "memory-management"
      ],
      "status": "pending_review",
      "reason": "Technical patterns detected in reviews can be reused across projects."
    }
  ]
}