{
  "run_id": "20260320_161115",
  "generated": "2026-03-20T16:29:36",
  "proposal_count": 1,
  "proposals": [
    {
      "title": "Product quality gap: Generic output detected",
      "type": "ux_insight",
      "lesson": "Creative Director rated output as 'fail'. Key issue: Generic output detected",
      "evidence": "CD review in run 20260320_161115: rating=fail",
      "source_run": "20260320_161115",
      "source_project": "askfin",
      "confidence": "hypothesis",
      "tags": [
        "product-quality",
        "cd-review"
      ],
      "status": "pending_review",
      "reason": "Product quality insights from CD reviews can improve future implementation prompts."
    }
  ]
}